{
  "name": "signup-03",
  "type": "registry:block",
  "description": "A compact branded registration card with responsive password fields and a mobile-safe route.",
  "dependencies": ["lucide-react-native"],
  "registryDependencies": [
    "card",
    "input",
    "label",
    "button",
    "icon",
    "text",
    "utils"
  ],
  "files": [
    {
      "src": "layout.tsx",
      "type": "registry:page",
      "target": "app/(auth)/_layout.tsx"
    },
    {
      "src": "sign-up.tsx",
      "type": "registry:page",
      "target": "app/(auth)/sign-up.tsx"
    },
    {
      "src": "components/signup-form.tsx",
      "type": "registry:component",
      "path": "components/signup-form.tsx"
    }
  ]
}
